ibkr_mcp_server/__init__.py
ibkr_mcp_server/cli.py
ibkr_mcp_server/client.py
ibkr_mcp_server/config.py
ibkr_mcp_server/exceptions.py
ibkr_mcp_server/models.py
ibkr_mcp_server/server.py
iflow_mcp_gaochx_ibkr_mcp_server-0.1.0.dist-info/METADATA
iflow_mcp_gaochx_ibkr_mcp_server-0.1.0.dist-info/WHEEL
iflow_mcp_gaochx_ibkr_mcp_server-0.1.0.dist-info/entry_points.txt
iflow_mcp_gaochx_ibkr_mcp_server-0.1.0.dist-info/licenses/LICENSE
iflow_mcp_gaochx_ibkr_mcp_server-0.1.0.dist-info/RECORD
