Metadata-Version: 2.4
Name: iflow-mcp_gaochx_ibkr-mcp-server
Version: 0.1.0
Summary: Interactive Brokers MCP Server for account management, trading operations, and market data
Project-URL: Homepage, https://github.com/yourusername/ibkr-mcp-server
Project-URL: Repository, https://github.com/yourusername/ibkr-mcp-server
Project-URL: Issues, https://github.com/yourusername/ibkr-mcp-server/issues
Author-email: Your Name <your.email@example.com>
License: MIT License
License-File: LICENSE
Keywords: api,interactive-brokers,mcp,trading
Classifier: Development Status :: 3 - Alpha
Classifier: Intended Audience :: Developers
Classifier: License :: OSI Approved :: MIT License
Classifier: Programming Language :: Python :: 3
Classifier: Programming Language :: Python :: 3.8
Classifier: Programming Language :: Python :: 3.9
Classifier: Programming Language :: Python :: 3.10
Classifier: Programming Language :: Python :: 3.11
Classifier: Programming Language :: Python :: 3.12
Classifier: Topic :: Office/Business :: Financial
Requires-Python: >=3.8
Requires-Dist: asyncio-mqtt>=0.13.0
Requires-Dist: fastmcp>=0.2.0
Requires-Dist: httpx>=0.24.0
Requires-Dist: ib-insync>=0.9.86
Requires-Dist: loguru>=0.7.0
Requires-Dist: mcp>=1.0.0
Requires-Dist: pydantic>=2.0.0
Requires-Dist: python-dotenv>=1.0.0
Requires-Dist: rich>=13.0.0
Requires-Dist: typer>=0.9.0
Requires-Dist: uvloop>=0.17.0; sys_platform != 'win32'
Provides-Extra: dev
Requires-Dist: black>=23.0.0; extra == 'dev'
Requires-Dist: flake8>=6.0.0; extra == 'dev'
Requires-Dist: isort>=5.12.0; extra == 'dev'
Requires-Dist: mypy>=1.5.0; extra == 'dev'
Requires-Dist: pre-commit>=3.0.0; extra == 'dev'
Requires-Dist: pytest-asyncio>=0.21.0; extra == 'dev'
Requires-Dist: pytest-cov>=4.0.0; extra == 'dev'
Requires-Dist: pytest>=7.0.0; extra == 'dev'
